{
	"$schema": "http://schema.management.azure.com/schemas/2015-01-01/deploymentTemplate.json#",
	"contentVersion": "1.0.0.0",
	"parameters": {
		"factoryName": {
			"type": "string",
			"metadata": "Data Factory name",
			"defaultValue": "Ringier"
		},
		"AzureDataLakeStorage1_accountKey": {
			"type": "secureString",
			"metadata": "Secure string for 'accountKey' of 'AzureDataLakeStorage1'"
		},
		"RestService2_clientSecret": {
			"type": "secureString",
			"metadata": "Secure string for 'clientSecret' of 'RestService2'"
		},
		"HttpServer1_password": {
			"type": "secureString",
			"metadata": "Secure string for 'password' of 'HttpServer1'"
		},
		"AzureSqlDatabase1_connectionString": {
			"type": "secureString",
			"metadata": "Secure string for 'connectionString' of 'AzureSqlDatabase1'"
		},
		"AzureBlobStorage1_connectionString": {
			"type": "secureString",
			"metadata": "Secure string for 'connectionString' of 'AzureBlobStorage1'"
		},
		"AzureSqlDatabase2_connectionString": {
			"type": "secureString",
			"metadata": "Secure string for 'connectionString' of 'AzureSqlDatabase2'"
		},
		"table_connectionString": {
			"type": "secureString",
			"metadata": "Secure string for 'connectionString' of 'table'"
		},
		"AzureSqlDatabase3_connectionString": {
			"type": "secureString",
			"metadata": "Secure string for 'connectionString' of 'AzureSqlDatabase3'"
		},
		"AzureDataLakeStorage1_properties_typeProperties_url": {
			"type": "string",
			"defaultValue": "https://leggacy.dfs.core.windows.net/"
		},
		"RestService1_properties_typeProperties_url": {
			"type": "string",
			"defaultValue": "https://newsapi.org/v2/everything?q=Apple&from=2022-08-24&sortBy=popularity&apiKey=5fb67aab8b0d492f956e4460b68bffbf"
		},
		"RestService2_properties_typeProperties_url": {
			"type": "string",
			"defaultValue": "https://newsapi.org/v2"
		},
		"RestService2_properties_typeProperties_clientId": {
			"type": "string",
			"defaultValue": "rupert@datascent.co"
		},
		"HttpServer1_properties_typeProperties_url": {
			"type": "string",
			"defaultValue": "https://newsapi.org/v2/"
		},
		"HttpServer1_properties_typeProperties_userName": {
			"type": "string",
			"defaultValue": "rupert@datascent"
		},
		"HttpServer2_properties_typeProperties_url": {
			"type": "string",
			"defaultValue": "https://newsapi.org/v2/everything"
		}
	},
	"variables": {
		"factoryId": "[concat('Microsoft.DataFactory/factories/', parameters('factoryName'))]"
	},
	"resources": [
		{
			"name": "[concat(parameters('factoryName'), '/AzureDataLakeStorage1')]",
			"type": "Microsoft.DataFactory/factories/linkedServices",
			"apiVersion": "2018-06-01",
			"properties": {
				"annotations": [],
				"type": "AzureBlobFS",
				"typeProperties": {
					"url": "[parameters('AzureDataLakeStorage1_properties_typeProperties_url')]",
					"accountKey": {
						"type": "SecureString",
						"value": "[parameters('AzureDataLakeStorage1_accountKey')]"
					}
				}
			},
			"dependsOn": []
		},
		{
			"name": "[concat(parameters('factoryName'), '/RestService1')]",
			"type": "Microsoft.DataFactory/factories/linkedServices",
			"apiVersion": "2018-06-01",
			"properties": {
				"annotations": [],
				"type": "RestService",
				"typeProperties": {
					"url": "[parameters('RestService1_properties_typeProperties_url')]",
					"enableServerCertificateValidation": false,
					"authenticationType": "Anonymous"
				}
			},
			"dependsOn": []
		},
		{
			"name": "[concat(parameters('factoryName'), '/RestService2')]",
			"type": "Microsoft.DataFactory/factories/linkedServices",
			"apiVersion": "2018-06-01",
			"properties": {
				"annotations": [],
				"type": "RestService",
				"typeProperties": {
					"url": "[parameters('RestService2_properties_typeProperties_url')]",
					"enableServerCertificateValidation": true,
					"authenticationType": "OAuth2ClientCredential",
					"clientId": "[parameters('RestService2_properties_typeProperties_clientId')]",
					"clientSecret": {
						"type": "SecureString",
						"value": "[parameters('RestService2_clientSecret')]"
					},
					"tokenEndpoint": "5fb67aab8b0d492f956e4460b68bffbf"
				}
			},
			"dependsOn": []
		},
		{
			"name": "[concat(parameters('factoryName'), '/HttpServer1')]",
			"type": "Microsoft.DataFactory/factories/linkedServices",
			"apiVersion": "2018-06-01",
			"properties": {
				"annotations": [],
				"type": "HttpServer",
				"typeProperties": {
					"url": "[parameters('HttpServer1_properties_typeProperties_url')]",
					"enableServerCertificateValidation": true,
					"authenticationType": "Basic",
					"userName": "[parameters('HttpServer1_properties_typeProperties_userName')]",
					"password": {
						"type": "SecureString",
						"value": "[parameters('HttpServer1_password')]"
					},
					"authHeaders": {
						"apiKey": {
							"type": "SecureString",
							"value": "**********"
						}
					}
				}
			},
			"dependsOn": []
		},
		{
			"name": "[concat(parameters('factoryName'), '/HttpServer2')]",
			"type": "Microsoft.DataFactory/factories/linkedServices",
			"apiVersion": "2018-06-01",
			"properties": {
				"annotations": [],
				"type": "HttpServer",
				"typeProperties": {
					"url": "[parameters('HttpServer2_properties_typeProperties_url')]",
					"enableServerCertificateValidation": true,
					"authenticationType": "Anonymous"
				}
			},
			"dependsOn": []
		},
		{
			"name": "[concat(parameters('factoryName'), '/AzureSqlDatabase1')]",
			"type": "Microsoft.DataFactory/factories/linkedServices",
			"apiVersion": "2018-06-01",
			"properties": {
				"annotations": [],
				"type": "AzureSqlDatabase",
				"typeProperties": {
					"connectionString": "[parameters('AzureSqlDatabase1_connectionString')]"
				}
			},
			"dependsOn": []
		},
		{
			"name": "[concat(parameters('factoryName'), '/AzureBlobStorage1')]",
			"type": "Microsoft.DataFactory/factories/linkedServices",
			"apiVersion": "2018-06-01",
			"properties": {
				"annotations": [],
				"type": "AzureBlobStorage",
				"typeProperties": {
					"connectionString": "[parameters('AzureBlobStorage1_connectionString')]"
				}
			},
			"dependsOn": []
		},
		{
			"name": "[concat(parameters('factoryName'), '/AzureSqlDatabase2')]",
			"type": "Microsoft.DataFactory/factories/linkedServices",
			"apiVersion": "2018-06-01",
			"properties": {
				"annotations": [],
				"type": "AzureSqlDatabase",
				"typeProperties": {
					"connectionString": "[parameters('AzureSqlDatabase2_connectionString')]"
				}
			},
			"dependsOn": []
		},
		{
			"name": "[concat(parameters('factoryName'), '/table')]",
			"type": "Microsoft.DataFactory/factories/linkedServices",
			"apiVersion": "2018-06-01",
			"properties": {
				"annotations": [],
				"type": "AzureSqlDatabase",
				"typeProperties": {
					"connectionString": "[parameters('table_connectionString')]"
				}
			},
			"dependsOn": []
		},
		{
			"name": "[concat(parameters('factoryName'), '/AzureSqlDatabase3')]",
			"type": "Microsoft.DataFactory/factories/linkedServices",
			"apiVersion": "2018-06-01",
			"properties": {
				"annotations": [],
				"type": "AzureSqlDatabase",
				"typeProperties": {
					"connectionString": "[parameters('AzureSqlDatabase3_connectionString')]"
				}
			},
			"dependsOn": []
		},
		{
			"name": "[concat(parameters('factoryName'), '/RestResource1')]",
			"type": "Microsoft.DataFactory/factories/datasets",
			"apiVersion": "2018-06-01",
			"properties": {
				"linkedServiceName": {
					"referenceName": "RestService1",
					"type": "LinkedServiceReference"
				},
				"annotations": [],
				"type": "RestResource",
				"typeProperties": {
					"relativeUrl": ""
				},
				"schema": []
			},
			"dependsOn": [
				"[concat(variables('factoryId'), '/linkedServices/RestService1')]"
			]
		},
		{
			"name": "[concat(parameters('factoryName'), '/AzureSqlTable1')]",
			"type": "Microsoft.DataFactory/factories/datasets",
			"apiVersion": "2018-06-01",
			"properties": {
				"linkedServiceName": {
					"referenceName": "AzureSqlDatabase3",
					"type": "LinkedServiceReference"
				},
				"annotations": [],
				"type": "AzureSqlTable",
				"schema": [],
				"typeProperties": {
					"schema": "dbo",
					"table": "rupert"
				}
			},
			"dependsOn": [
				"[concat(variables('factoryId'), '/linkedServices/AzureSqlDatabase3')]"
			]
		},
		{
			"name": "[concat(parameters('factoryName'), '/pipeline1')]",
			"type": "Microsoft.DataFactory/factories/pipelines",
			"apiVersion": "2018-06-01",
			"properties": {
				"activities": [
					{
						"name": "Copy data1",
						"type": "Copy",
						"dependsOn": [],
						"policy": {
							"timeout": "7.00:00:00",
							"retry": 0,
							"retryIntervalInSeconds": 30,
							"secureOutput": false,
							"secureInput": false
						},
						"userProperties": [],
						"typeProperties": {
							"source": {
								"type": "RestSource",
								"httpRequestTimeout": "00:01:40",
								"requestInterval": "00.00:00:00.010",
								"requestMethod": "GET",
								"paginationRules": {
									"supportRFC5988": "true"
								}
							},
							"sink": {
								"type": "AzureSqlSink",
								"writeBehavior": "insert",
								"sqlWriterUseTableLock": false,
								"tableOption": "autoCreate",
								"disableMetricsCollection": false
							},
							"enableStaging": false,
							"translator": {
								"type": "TabularTranslator",
								"mappings": [
									{
										"source": {
											"path": "$['status']"
										},
										"sink": {
											"name": "status"
										}
									},
									{
										"source": {
											"path": "$['totalResults']"
										},
										"sink": {
											"name": "totalResults"
										}
									},
									{
										"source": {
											"path": "[['source']['id']"
										},
										"sink": {
											"name": "id"
										}
									},
									{
										"source": {
											"path": "[['source']['name']"
										},
										"sink": {
											"name": "name"
										}
									},
									{
										"source": {
											"path": "[['author']"
										},
										"sink": {
											"name": "author"
										}
									},
									{
										"source": {
											"path": "[['title']"
										},
										"sink": {
											"name": "title"
										}
									},
									{
										"source": {
											"path": "[['description']"
										},
										"sink": {
											"name": "description"
										}
									},
									{
										"source": {
											"path": "[['url']"
										},
										"sink": {
											"name": "url"
										}
									},
									{
										"source": {
											"path": "[['urlToImage']"
										},
										"sink": {
											"name": "urlToImage"
										}
									},
									{
										"source": {
											"path": "[['publishedAt']"
										},
										"sink": {
											"name": "publishedAt"
										}
									},
									{
										"source": {
											"path": "[['content']"
										},
										"sink": {
											"name": "content"
										}
									}
								],
								"collectionReference": "$['articles']",
								"mapComplexValuesToString": true
							}
						},
						"inputs": [
							{
								"referenceName": "RestResource1",
								"type": "DatasetReference",
								"parameters": {}
							}
						],
						"outputs": [
							{
								"referenceName": "AzureSqlTable1",
								"type": "DatasetReference",
								"parameters": {}
							}
						]
					}
				],
				"policy": {
					"elapsedTimeMetric": {},
					"cancelAfter": {}
				},
				"annotations": []
			},
			"dependsOn": [
				"[concat(variables('factoryId'), '/datasets/RestResource1')]",
				"[concat(variables('factoryId'), '/datasets/AzureSqlTable1')]"
			]
		}
	]
}